pyhandsontable/.DS_Store
pyhandsontable/__init__.py
pyhandsontable/core.py
pyhandsontable/pagination.py
pyhandsontable/templates/.DS_Store
pyhandsontable/templates/handsontable.full.min.css
pyhandsontable/templates/handsontable.full.min.js
pyhandsontable/templates/sheet.html
pyhandsontable/templates/sheet.js
pyhandsontable-0.3.dist-info/LICENSE
pyhandsontable-0.3.dist-info/WHEEL
pyhandsontable-0.3.dist-info/METADATA
pyhandsontable-0.3.dist-info/RECORD
