Metadata-Version: 2.1
Name: pyhandsontable
Version: 0.3
Summary: View a list of dictionaries or a 2-D array, in HandsOnTable, in Jupyter Notebook.
Home-page: https://github.com/patarapolw/pyhandsontable
License: MIT
Keywords: handsontable
Author: Pacharapol Withayasakpunt
Author-email: patarapolw@gmail.com
Requires-Python: >=3.5
Classifier: License :: OSI Approved :: MIT License
Classifier: Programming Language :: Python :: 3
Classifier: Programming Language :: Python :: 3.5
Classifier: Programming Language :: Python :: 3.6
Classifier: Programming Language :: Python :: 3.7
Requires-Dist: jinja2 (>=2.10,<3.0)
Requires-Dist: jupyter (>=1.0,<2.0)
Requires-Dist: notebook (>=5.6,<6.0)
